{"AndroidX annotation library": {"length": 10695, "start": 1431}, "Dagger": {"length": 11358, "start": 12137}, "Error Prone": {"length": 11357, "start": 23511}, "Google Auto": {"length": 11358, "start": 34884}, "Guava JDK7": {"length": 11362, "start": 46257}, "JSR 250": {"length": 11358, "start": 57631}, "JSR 305": {"length": 1602, "start": 69001}, "JSR 330": {"length": 11365, "start": 70615}, "JSpecify": {"length": 11358, "start": 81993}, "Kotlin": {"length": 102807, "start": 115133}, "Play Core Software Development Kit": {"length": 1360, "start": 39}, "archive_patcher": {"length": 12521, "start": 93371}, "p2putils": {"length": 9217, "start": 105905}}